sphinx_matlabdoc_builder/__init__.py
sphinx_matlabdoc_builder/matlab_doc_builder.py
sphinx_matlabdoc_builder-0.1.2.dist-info/LICENSE
sphinx_matlabdoc_builder-0.1.2.dist-info/METADATA
sphinx_matlabdoc_builder-0.1.2.dist-info/WHEEL
sphinx_matlabdoc_builder-0.1.2.dist-info/entry_points.txt
sphinx_matlabdoc_builder-0.1.2.dist-info/top_level.txt
sphinx_matlabdoc_builder-0.1.2.dist-info/RECORD
