Metadata-Version: 2.1
Name: sphinx-matlabdoc-builder
Version: 0.1.2
Summary: A Sphinx extension for generating Matlab HTML docs.
Home-page: https://github.com/ilent2/sphinx-matlabdoc-builder
Author: Isaac Lenton
Author-email: isaac@isuniversal.com
Maintainer: Isaac Lenton
Maintainer-email: isaac@isuniversal.com
License: BSD
Download-URL: https://pypi.org/project/sphinx-matlabdoc-builder
Keywords: sphinx docs documentation matlab
Platform: any
Classifier: Development Status :: 4 - Beta
Classifier: Environment :: Console
Classifier: Environment :: Web Environment
Classifier: Intended Audience :: Developers
Classifier: License :: OSI Approved :: BSD License
Classifier: Operating System :: OS Independent
Classifier: Programming Language :: Python
Classifier: Topic :: Documentation
Classifier: Topic :: Utilities
Classifier: Framework :: Sphinx :: Extension
